skymarshal/__init__.py
skymarshal/__main__.py
skymarshal/common_util.py
skymarshal/emit_cpp.py
skymarshal/emit_djinni.py
skymarshal/emit_helpers.py
skymarshal/emit_java.py
skymarshal/emit_lcmout.py
skymarshal/emit_proto.py
skymarshal/emit_python.py
skymarshal/emit_typescript.py
skymarshal/language_plugin.py
skymarshal/lextab_py2.py
skymarshal/lextab_py3.py
skymarshal/package_map.py
skymarshal/parser.py
skymarshal/py.typed
skymarshal/regenerate_lextab.py
skymarshal/skymarshal.py
skymarshal/syntax_tree.py
skymarshal/tokenizer.py
skymarshal/templates/aggregate.hpp.template
skymarshal/templates/djinni_converter.cc.template
skymarshal/templates/djinni_converter.h.template
skymarshal/templates/djinni_idl.djinni.template
skymarshal/templates/enumtype.hpp.template
skymarshal/templates/forward.hpp.template
skymarshal/templates/lcmtype.hpp.template
skymarshal/templates/lcmtype.java.template
skymarshal/templates/proto_enum.proto.template
skymarshal/templates/proto_struct.proto.template
skymarshal/templates/protolcm.cc.template
skymarshal/templates/protolcm.h.template
skymarshal/templates/python_enum.py.template
skymarshal/templates/python_enum_default_wrapper.py.template
skymarshal/templates/python_init.py.template
skymarshal/templates/python_struct.py.template
skymarshal/templates/python_struct_default_wrapper.py.template
skymarshal/templates/typescript_enum.ts.template
skymarshal/templates/typescript_struct.ts.template
skymarshal/typescript_core/src/decoder.ts
skymarshal/typescript_core/src/encoder.ts
skymarshal/typescript_core/src/enum.ts
skymarshal/typescript_core/src/index.ts
skymarshal/typescript_core/src/lcm.ts
skymarshal/typescript_core/src/reflection.ts
skymarshal/typescript_core/src/types.ts
skymarshal-0.10.1.dist-info/licenses/LICENSE
skymarshal-0.10.1.dist-info/METADATA
skymarshal-0.10.1.dist-info/WHEEL
skymarshal-0.10.1.dist-info/top_level.txt
skymarshal-0.10.1.dist-info/RECORD
