Metadata-Version: 2.4
Name: skymarshal
Version: 0.10.1
Summary: Python implementation of marshalling for LCM messages
Author: Skydio, Inc.
License: LGPL-2.1-or-later
Project-URL: Bug Tracker, https://github.com/symforce-org/symforce/issues
Project-URL: Source, https://github.com/symforce-org/symforce/tree/main/third_party/skymarshal
Classifier: Intended Audience :: Developers
Classifier: Development Status :: 4 - Beta
Classifier: License :: OSI Approved :: GNU Lesser General Public License v2 or later (LGPLv2+)
Classifier: Programming Language :: Python :: 3
Classifier: Topic :: Software Development :: Code Generators
Classifier: Topic :: Software Development :: Libraries :: Python Modules
Classifier: Operating System :: OS Independent
Requires-Python: >=3.8
License-File: LICENSE
Requires-Dist: argh
Requires-Dist: jinja2
Requires-Dist: numpy
Requires-Dist: ply
Dynamic: license-file
